change_sequence/__main__.py
change_sequence/change_seq.py
change_sequence/test_convs.py
change_sequence-1.0.2.data/scripts/test_convs.py
change_sequence-1.0.2.dist-info/METADATA
change_sequence-1.0.2.dist-info/WHEEL
change_sequence-1.0.2.dist-info/top_level.txt
change_sequence-1.0.2.dist-info/RECORD
