Metadata-Version: 2.1
Name: change-sequence
Version: 1.0.2
Summary: Converting strings project
License: MIT License
Requires: pytest
